qlibs/__init__.py
qlibs/collections.py
qlibs/matrix.py
qlibs/modelloader.py
qlibs/modelrenderer.py
qlibs/opt.py
qlibs/qopt.py
qlibs/qvec.py
qlibs/resource_loader.py
qlibs/test.py
qlibs/test2.py
qlibs/test3.py
qlibs/test4.py
qlibs/testrunner.py
qlibs/util.py
qlibs/vec.py
qlibs/fileworks/__init__.py
qlibs/fonts/__init__.py
qlibs/fonts/font_render.py
qlibs/fonts/font_search.py
qlibs/gui/__init__.py
qlibs/gui/basic_shapes.py
qlibs/gui/constants.py
qlibs/gui/enums.py
qlibs/gui/helper.py
qlibs/gui/qgui.py
qlibs/gui/window.py
qlibs/gui/nodes/GuiNode.py
qlibs/gui/nodes/GuiNodeButton.py
qlibs/gui/nodes/GuiNodeHighlighted.py
qlibs/gui/nodes/GuiNodeIncrementalText.py
qlibs/gui/nodes/GuiNodeText.py
qlibs/gui/nodes/__init__.py
qlibs/gui/window_provider/__init__.py
qlibs/gui/window_provider/sdl2_based.py
qlibs/gui/window_provider/window_provider.py
qlibs/math/__init__.py
qlibs/math/matrix.py
qlibs/math/opt.py
qlibs/math/vec.py
qlibs/models/__init__.py
qlibs/models/compoundmodel.py
qlibs/models/modelloader.py
qlibs/models/modelrenderer.py
qlibs/net/TCPlink.py
qlibs/net/UDPlink.py
qlibs/net/__init__.py
qlibs/net/asyncsocket.py
qlibs/net/connection.py
qlibs/net/qpacket.py
qlibs/resources/__init__.py
qlibs/resources/resource_loader.py
qlibs/resources/resource_manager.py
qlibs/resources/__pycache__/__init__.cpython-37.pyc
qlibs/resources/__pycache__/resource_loader.cpython-37.pyc
qlibs/resources/__pycache__/resource_manager.cpython-37.pyc
qlibs/resources/dll/SDL2.dll
qlibs/resources/dll/SLD2_LICENSE.txt
qlibs/resources/shaders/basic_textures_fragment_shader.glsh
qlibs/resources/shaders/basic_textures_shader.glsh
qlibs/resources/storage/shaders/drawer.frag
qlibs/resources/storage/shaders/drawer.vert
qlibs/resources/storage/shaders/lighting.frag
qlibs/resources/storage/shaders/modelrender.vert
qlibs/resources/storage/shaders/text.frag
qlibs/resources/storage/shaders/text.vert
qlibs/resources/storage/text/linux_font_list
qlibs-0.2.0.dist-info/LICENSE.txt
qlibs-0.2.0.dist-info/METADATA
qlibs-0.2.0.dist-info/WHEEL
qlibs-0.2.0.dist-info/top_level.txt
qlibs-0.2.0.dist-info/RECORD
