Metadata-Version: 2.1
Name: qlibs
Version: 0.2.0
Summary: Networking, gui, math and more
Home-page: https://bitbucket.org/IntQuant/qlibs/
Author: IQuant
Author-email: quant3234@gmail.com
License: UNKNOWN
Platform: UNKNOWN
Classifier: Programming Language :: Python :: 3
Classifier: License :: OSI Approved :: MIT License
Classifier: Operating System :: OS Independent
Requires-Dist: moderngl
Requires-Dist: glfw
Provides-Extra: full
Requires-Dist: pillow ; extra == 'full'
Requires-Dist: freetype-py ; extra == 'full'
